.gitignore
.travis.yml
CHANGES.rst
MANIFEST.in
README.rst
TODO.rst
development.ini
setup.cfg
setup.py
kotti_gallery/__init__.py
kotti_gallery/fanstatic.py
kotti_gallery/resources.py
kotti_gallery/views.py
kotti_gallery.egg-info/PKG-INFO
kotti_gallery.egg-info/SOURCES.txt
kotti_gallery.egg-info/dependency_links.txt
kotti_gallery.egg-info/entry_points.txt
kotti_gallery.egg-info/not-zip-safe
kotti_gallery.egg-info/requires.txt
kotti_gallery.egg-info/top_level.txt
kotti_gallery/locale/kotti_gallery.pot
kotti_gallery/locale/de/LC_MESSAGES/kotti_gallery.mo
kotti_gallery/locale/de/LC_MESSAGES/kotti_gallery.po
kotti_gallery/static/kotti_gallery.css
kotti_gallery/static/kotti_gallery.min.css
kotti_gallery/static/transparent.gif
kotti_gallery/templates/.DS_Store
kotti_gallery/templates/gallery-view.pt
kotti_gallery/templates/modal.pt
kotti_gallery/tests/browser.txt
kotti_gallery/tests/sendeschluss.jpg