Metadata-Version: 1.0
Name: kotti-gallery
Version: 0.2.2
Summary: Add an image gallery to your Kotti site
Home-page: https://github.com/disko/kotti_gallery
Author: Andreas Kaiser
Author-email: disko@binary-punks.com
License: BSD-derived (http://www.repoze.org/LICENSE.txt)
Keywords: image gallery bootstrap kotti cms pylons pyramid
Platform: UNKNOWN
Classifier: Programming Language :: Python
Classifier: Framework :: Pylons
Classifier: Topic :: Internet :: WWW/HTTP
Classifier: Topic :: Internet :: WWW/HTTP :: Dynamic Content
Classifier: Topic :: Internet :: WWW/HTTP :: WSGI :: Application
Classifier: License :: Repoze Public License
